travis_tox/generate.py
travis_tox/__init__.py
travis_tox-0.1.0.dist-info/metadata.json
travis_tox-0.1.0.dist-info/zip-safe
travis_tox-0.1.0.dist-info/WHEEL
travis_tox-0.1.0.dist-info/top_level.txt
travis_tox-0.1.0.dist-info/METADATA
travis_tox-0.1.0.dist-info/DESCRIPTION.rst
travis_tox-0.1.0.dist-info/RECORD
