Metadata-Version: 2.0
Name: travis-tox
Version: 0.1.0
Summary: Generate your travis config from tox
Home-page: https://github.com/graingert/travis-tox
Author: Thomas Grainger
Author-email: travis-tox@graingert.co.uk
License: UNKNOWN
Keywords: travis,tox
Platform: UNKNOWN
